singhlab/__init__.py
singhlab/utils/__init__.py
singhlab/utils/decorators/__init__.py
singhlab/utils/decorators/bootstrap.py
singhlab/utils/decorators/manage_storage.py
singhlab/utils/decorators/run_with_seed.py
singhlab/utils/nas_stager/__init__.py
singhlab/utils/nas_stager/nas_stager.py
singhlab-0.0.2.dist-info/licenses/LICENSE
singhlab-0.0.2.dist-info/METADATA
singhlab-0.0.2.dist-info/WHEEL
singhlab-0.0.2.dist-info/top_level.txt
singhlab-0.0.2.dist-info/RECORD
