Metadata-Version: 2.4
Name: singhlab
Version: 0.0.2
Summary: General functions useful to members of Rohit Singh lab.
Author-email: Aditya Parekh <aditya.parekh@duke.edu>
Project-URL: Homepage, https://github.com/rohitsinghlab/singhlab-main
Project-URL: Bug Tracker, https://github.com/rohitsinghlab/singhlab-main/issues
Classifier: Programming Language :: Python :: 3
Classifier: License :: OSI Approved :: MIT License
Classifier: Operating System :: OS Independent
License-File: LICENSE
Requires-Dist: setuptools
Requires-Dist: numpy
Dynamic: license-file
